pearll/__init__.py
pearll/agents/__init__.py
pearll/agents/a2c.py
pearll/agents/adames.py
pearll/agents/base_agents.py
pearll/agents/cem_rl.py
pearll/agents/ddpg.py
pearll/agents/dqn.py
pearll/agents/dyna.py
pearll/agents/es.py
pearll/agents/ga.py
pearll/agents/ppo.py
pearll/agents/templates.py
pearll/buffers/__init__.py
pearll/buffers/base_buffer.py
pearll/buffers/her_buffer.py
pearll/buffers/replay_buffer.py
pearll/buffers/rollout_buffer.py
pearll/callbacks/__init__.py
pearll/callbacks/base_callback.py
pearll/callbacks/checkpoint_callback.py
pearll/common/enumerations.py
pearll/common/logging_.py
pearll/common/type_aliases.py
pearll/common/utils.py
pearll/demo.py
pearll/explorers/__init__.py
pearll/explorers/base_explorer.py
pearll/explorers/gaussian_explorer.py
pearll/models/__init__.py
pearll/models/actor_critics.py
pearll/models/encoders.py
pearll/models/environment.py
pearll/models/heads.py
pearll/models/torsos.py
pearll/models/utils.py
pearll/plot.py
pearll/settings.py
pearll/signal_processing/__init__.py
pearll/signal_processing/advantage_estimators.py
pearll/signal_processing/crossover_operators.py
pearll/signal_processing/mutation_operators.py
pearll/signal_processing/return_estimators.py
pearll/signal_processing/sample_estimators.py
pearll/signal_processing/selection_operators.py
pearll/updaters/__init__.py
pearll/updaters/actors.py
pearll/updaters/critics.py
pearll/updaters/environment.py
pearll/updaters/evolution.py
pearll-0.4.1.dist-info/LICENSE
pearll-0.4.1.dist-info/WHEEL
pearll-0.4.1.dist-info/METADATA
pearll-0.4.1.dist-info/RECORD
